odoo/addons/partner_contact_access_link/README.rst
odoo/addons/partner_contact_access_link/__init__.py
odoo/addons/partner_contact_access_link/__manifest__.py
odoo/addons/partner_contact_access_link/i18n/ca.po
odoo/addons/partner_contact_access_link/i18n/es.po
odoo/addons/partner_contact_access_link/i18n/fr.po
odoo/addons/partner_contact_access_link/i18n/hr.po
odoo/addons/partner_contact_access_link/i18n/it.po
odoo/addons/partner_contact_access_link/i18n/partner_contact_access_link.pot
odoo/addons/partner_contact_access_link/i18n/pt_BR.po
odoo/addons/partner_contact_access_link/models/__init__.py
odoo/addons/partner_contact_access_link/models/res_partner.py
odoo/addons/partner_contact_access_link/readme/CONTRIBUTORS.md
odoo/addons/partner_contact_access_link/readme/DESCRIPTION.md
odoo/addons/partner_contact_access_link/readme/USAGE.md
odoo/addons/partner_contact_access_link/static/description/full-form.gif
odoo/addons/partner_contact_access_link/static/description/icon.png
odoo/addons/partner_contact_access_link/static/description/index.html
odoo/addons/partner_contact_access_link/tests/__init__.py
odoo/addons/partner_contact_access_link/tests/test_partner_contact_access_link.py
odoo/addons/partner_contact_access_link/views/res_partner_views.xml
odoo_addon_partner_contact_access_link-19.0.1.0.0.5.dist-info/METADATA
odoo_addon_partner_contact_access_link-19.0.1.0.0.5.dist-info/WHEEL
odoo_addon_partner_contact_access_link-19.0.1.0.0.5.dist-info/top_level.txt
odoo_addon_partner_contact_access_link-19.0.1.0.0.5.dist-info/RECORD
