Metadata-Version: 2.1
Name: odoo-addon-partner_contact_access_link
Version: 19.0.1.0.0.5
Requires-Dist: odoo==19.0.*
Summary: Allow to visit the full contact form from a company
Home-page: https://github.com/OCA/partner-contact
License: AGPL-3
Author: Tecnativa, Odoo Community Association (OCA)
Author-email: support@odoo-community.org
Classifier: Programming Language :: Python
Classifier: Framework :: Odoo
Classifier: Framework :: Odoo :: 19.0
Classifier: License :: OSI Approved :: GNU Affero General Public License v3
Classifier: Development Status :: 5 - Production/Stable
